live_cells/__init__.py
live_cells/async_state.py
live_cells/await_cell.py
live_cells/boolean.py
live_cells/cell.py
live_cells/changes_only_state.py
live_cells/compute_cell.py
live_cells/compute_state.py
live_cells/computed.py
live_cells/constant_cell.py
live_cells/dependent_cell.py
live_cells/dynamic_compute_cell.py
live_cells/error_handling.py
live_cells/exceptions.py
live_cells/extension.py
live_cells/keys.py
live_cells/maybe.py
live_cells/mutable_cell.py
live_cells/numeric.py
live_cells/observer_state.py
live_cells/peek_cell.py
live_cells/persistent_stateful_cell.py
live_cells/stateful_cell.py
live_cells/tracking.py
live_cells/wait_cell.py
live_cells/waited.py
live_cells/watch.py
live_cells_py-0.2.0.dist-info/licenses/LICENSE
live_cells_py-0.2.0.dist-info/METADATA
live_cells_py-0.2.0.dist-info/WHEEL
live_cells_py-0.2.0.dist-info/top_level.txt
live_cells_py-0.2.0.dist-info/RECORD
