Metadata-Version: 2.4
Name: live-cells-py
Version: 0.2.0
Summary: A reactive programming library for Python ported from Live Cells for Dart
Home-page: https://github.com/alex-gutev/live_cells_py
Author: Alexander Gutev
Author-email: alex.gutev@gmail.com
Classifier: Programming Language :: Python :: 3
Classifier: License :: OSI Approved :: BSD License
Classifier: Operating System :: OS Independent
Requires-Python: >=3.6
License-File: LICENSE
Dynamic: author
Dynamic: author-email
Dynamic: classifier
Dynamic: description
Dynamic: description-content-type
Dynamic: home-page
Dynamic: license-file
Dynamic: requires-python
Dynamic: summary
